odoo/addons/stock_location_zone/README.rst
odoo/addons/stock_location_zone/__init__.py
odoo/addons/stock_location_zone/__manifest__.py
odoo/addons/stock_location_zone/i18n/es.po
odoo/addons/stock_location_zone/i18n/it.po
odoo/addons/stock_location_zone/i18n/stock_location_zone.pot
odoo/addons/stock_location_zone/i18n/zh_CN.po
odoo/addons/stock_location_zone/models/__init__.py
odoo/addons/stock_location_zone/models/stock_location.py
odoo/addons/stock_location_zone/readme/CONTRIBUTORS.md
odoo/addons/stock_location_zone/readme/CREDITS.md
odoo/addons/stock_location_zone/readme/DESCRIPTION.md
odoo/addons/stock_location_zone/static/description/icon.png
odoo/addons/stock_location_zone/static/description/index.html
odoo/addons/stock_location_zone/tests/__init__.py
odoo/addons/stock_location_zone/tests/test_stock_location_zone.py
odoo/addons/stock_location_zone/views/stock_location.xml
odoo_addon_stock_location_zone-18.0.1.0.0.5.dist-info/METADATA
odoo_addon_stock_location_zone-18.0.1.0.0.5.dist-info/WHEEL
odoo_addon_stock_location_zone-18.0.1.0.0.5.dist-info/top_level.txt
odoo_addon_stock_location_zone-18.0.1.0.0.5.dist-info/RECORD
